pydalle/__init__.py
pydalle/functional/__init__.py
pydalle/functional/assumptions.py
pydalle/functional/types.py
pydalle/functional/utils.py
pydalle/functional/api/__init__.py
pydalle/functional/api/flow/__init__.py
pydalle/functional/api/flow/auth0.py
pydalle/functional/api/flow/labs.py
pydalle/functional/api/request/__init__.py
pydalle/functional/api/request/auth0.py
pydalle/functional/api/request/labs.py
pydalle/functional/api/response/__init__.py
pydalle/functional/api/response/labs.py
pydalle/imperative/__init__.py
pydalle/imperative/api/__init__.py
pydalle/imperative/api/auth0.py
pydalle/imperative/api/labs.py
pydalle/imperative/client/__init__.py
pydalle/imperative/client/dalle.py
pydalle/imperative/client/responses.py
pydalle/imperative/client/utils.py
pydalle/imperative/outside/__init__.py
pydalle/imperative/outside/files.py
pydalle/imperative/outside/internet.py
pydalle/imperative/outside/np.py
pydalle/imperative/outside/pil.py
pydalle/imperative/outside/sysrand.py
pydalle-0.2.0.dist-info/LICENSE
pydalle-0.2.0.dist-info/METADATA
pydalle-0.2.0.dist-info/WHEEL
pydalle-0.2.0.dist-info/top_level.txt
pydalle-0.2.0.dist-info/RECORD
