Metadata-Version: 2.1
Name: pydalle
Version: 0.2.0
Summary: A library for providing programmatic access to the DALL·E 2 API
Home-page: https://github.com/nottheswimmer/dalle
Author: Michael Phelps
Author-email: michaelphelps@nottheswimmer.org
License: MIT
Classifier: Development Status :: 4 - Beta
Classifier: Intended Audience :: Developers
Classifier: License :: OSI Approved :: MIT License
Classifier: Programming Language :: Python :: 3
Classifier: Programming Language :: Python :: 3.8
Classifier: Programming Language :: Python :: 3.9
Classifier: Programming Language :: Python :: 3.10
Classifier: Topic :: Software Development :: Libraries
Classifier: Topic :: Software Development :: Libraries :: Python Modules
License-File: LICENSE
Provides-Extra: all
Requires-Dist: aiofiles ; extra == 'all'
Requires-Dist: aiohttp ; extra == 'all'
Requires-Dist: requests ; extra == 'all'
Requires-Dist: pillow ; extra == 'all'
Requires-Dist: numpy ; extra == 'all'
Provides-Extra: async
Requires-Dist: aiofiles ; extra == 'async'
Requires-Dist: aiohttp ; extra == 'async'
Provides-Extra: images
Requires-Dist: pillow ; extra == 'images'
Requires-Dist: numpy ; extra == 'images'
Provides-Extra: sync
Requires-Dist: requests ; extra == 'sync'
